pop_pricer/__init__.py
pop_pricer/pricer.py
pop_pricer-0.1.4.dist-info/LICENSE.md
pop_pricer-0.1.4.dist-info/METADATA
pop_pricer-0.1.4.dist-info/WHEEL
pop_pricer-0.1.4.dist-info/RECORD
